{
    "wallpaper": "/home/lecongkhoiviet/.config/wpg/wallpapers/pjhanekawa.png",
    "alpha": "100",

    "special": {
        "background": "#3c3c3c",
        "foreground": "#fbfbfb",
        "cursor": "#fbfbfb"
    },
    "colors": {
        "color0": "#3c3c3c",
        "color1": "#d69a9a",
        "color2": "#86a986",
        "color3": "#dac896",
        "color4": "#72aaae",
        "color5": "#e792cc",
        "color6": "#99eaee",
        "color7": "#e5e5d4",
        "color8": "#aaaaaa",
        "color9": "#ffb0b0",
        "color10": "#9aef9a",
        "color11": "#ffffab",
        "color12": "#81edf4",
        "color13": "#ffa5ff",
        "color14": "#adffff",
        "color15": "#fbfbfb"
    }
}
